maplab/__init__.py
maplab/foliumap.py
maplab/maplab.py
maplab-0.2.2.dist-info/LICENSE
maplab-0.2.2.dist-info/METADATA
maplab-0.2.2.dist-info/WHEEL
maplab-0.2.2.dist-info/dependency_links.txt
maplab-0.2.2.dist-info/top_level.txt
maplab-0.2.2.dist-info/RECORD
