Metadata-Version: 2.1
Name: maplab
Version: 0.2.2
Summary: Python Boilerplate contains all the boilerplate you need to create a Python package.
Home-page: https://github.com/hwilli72/maplab
Author: Hannah Williams
Author-email: hwilli72@vols.utk.edu
License: MIT license
Keywords: maplab
Classifier: Development Status :: 2 - Pre-Alpha
Classifier: Intended Audience :: Developers
Classifier: License :: OSI Approved :: MIT License
Classifier: Natural Language :: English
Classifier: Programming Language :: Python :: 3
Classifier: Programming Language :: Python :: 3.7
Classifier: Programming Language :: Python :: 3.8
Classifier: Programming Language :: Python :: 3.9
Classifier: Programming Language :: Python :: 3.10
Requires-Python: >=3.7
License-File: LICENSE
Requires-Dist: folium
Requires-Dist: ipyleaflet
Requires-Dist: pandas
Requires-Dist: openpyxl
Requires-Dist: httpx
Requires-Dist: geopandas
